happyci/__init__.py
happyci/__main__.py
happyci/_version.py
happyci/logger.py
happyci/stage_runner.py
happyci/plugins/__init__.py
happyci/plugins/command.py
happyci/plugins/docker.py
happyci/plugins/git.py
happyci/plugins/mvn.py
happyci/plugins/script.py
happy_ci-0.1.0.dist-info/LICENSE
happy_ci-0.1.0.dist-info/METADATA
happy_ci-0.1.0.dist-info/WHEEL
happy_ci-0.1.0.dist-info/entry_points.txt
happy_ci-0.1.0.dist-info/top_level.txt
happy_ci-0.1.0.dist-info/RECORD
