Metadata-Version: 2.1
Name: happy-ci
Version: 0.1.0
Summary: A lightweight CI/CD program
Home-page: https://gitee.com/xing-phil/happy-ci
Author: Xing Fei
Author-email: xfei-q@qq.com
License: UNKNOWN
Project-URL: Bug Tracker, https://gitee.com/xing-phil/happy-ci/issues
Platform: UNKNOWN
Classifier: Programming Language :: Python :: 3
Classifier: License :: OSI Approved :: MIT License
Classifier: Operating System :: OS Independent
Requires-Python: >=3.6
License-File: LICENSE
Requires-Dist: PyYAML
